setup.py
mangafox_dl.egg-info/PKG-INFO
mangafox_dl.egg-info/SOURCES.txt
mangafox_dl.egg-info/dependency_links.txt
mangafox_dl.egg-info/entry_points.txt
mangafox_dl.egg-info/top_level.txt
mangafoxdl/__init__.py
mangafoxdl/__main__.py