Metadata-Version: 1.1
Name: mangafox-dl
Version: 1.1.5
Summary: A simple downloader for https://www.mangafox.la
Home-page: https://github.com/Dragneel1234
Author: Dragneel1234
Author-email: blwal7057@gmail.com
License: GPL-3.0
Platform: UNKNOWN
Classifier: Environment :: Console
Classifier: Topic :: Utilities
